Workbook

Sheet Casos
A1: 16 casos de control — retenciones Colombia 2026
A2: Cada fila es un caso independiente. No sumar bases entre casos. UVT 2026: $52.374.
A4: # | B4: Caso | C4: Concepto | D4: Comprador | E4: Proveedor | F4: Base | G4: IVA | H4: Total | I4: RF % | J4: RF | K4: RIVA % | L4: RIVA | M4: RICA % | N4: RICA | O4: Total retenciones | P4: Neto | Q4: Asiento | R4: Documentos | S4: Errores a evitar | T4: Nota | U4: Chequeo
A5: 1 | B5: Servicio general, proveedor declarante, comprador SAS normal | C5: Servicio general | D5: SAS normal; agente RF; no RIVA/RICA | E5: Persona jurídica declarante; no gran contribuyente | F5: 2000000 | G5: 380000 | H5: 2380000 | I5: 0.04 | J5: 80000 | K5: 0 | L5: 0 | M5: 0 | N5: 0 | O5: 80000 | P5: 2300000 | Q5: D 5135 / D 240805 / C 220505; pago C 236525 | R5: Factura, certificado RF, comprobante, Formulario 350 | S5: No calcular RF sobre el total; no practicar RIVA sin ser agente | T5: Caso base de servicio general. | U5: =H5-O5-P5
A6: 2 | B6: Servicio general, proveedor no declarante | C6: Servicio general | D6: SAS normal; agente RF; no RIVA/RICA | E6: Persona natural no declarante; responsable de IVA | F6: 500000 | G6: 95000 | H6: 595000 | I6: 0.06 | J6: 30000 | K6: 0 | L6: 0 | M6: 0 | N6: 0 | O6: 30000 | P6: 565000 | Q6: D 5135 / D 240805 / C 220505; pago C 236525 | R6: RUT, certificación de no declarante, factura, certificado RF, Formulario 350 | S6: Aplicar 4% en lugar de 6%; no documentar la condición de no declarante | T6: La base supera 2 UVT. | U6: =H6-O6-P6
A7: 3 | B7: Servicio por debajo del mínimo | C7: Servicio general | D7: SAS normal | E7: Persona natural no declarante; responsable de IVA | F7: 90000 | G7: 17100 | H7: 107100 | I7: 0 | J7: 0 | K7: 0 | L7: 0 | M7: 0 | N7: 0 | O7: 0 | P7: 107100 | Q7: D 5135 / D 240805 / C 111005 (o proveedores) | R7: Factura y comprobante de pago; no hay certificado de retención | S7: Retener sobre $90.000; aplicar reteIVA sin verificar el mínimo; fragmentar la operación | T7: Base inferior a 2 UVT ($104.748): no hay retención. | U7: =H7-O7-P7
A8: 4 | B8: Base exactamente en 2 UVT | C8: Servicio general | D8: Gran contribuyente; agente RF y RIVA | E8: Persona jurídica declarante; no gran contribuyente | F8: 104748 | G8: 19902.12 | H8: 124650.12 | I8: 0.04 | J8: 4189.92 | K8: 0.15 | L8: 2985.32 | M8: 0 | N8: 0 | O8: 7175.24 | P8: 117474.88 | Q8: D 5135 / D 240805 / C 220505; pago C 236525 / C 236701 | R8: Factura, certificado RF, certificado reteIVA, comprobante, Formulario 350 | S8: Redondear de forma inconsistente; no definir política de redondeo | T8: Valores exactos. Redondeo a peso: RF $4.190; RIVA $2.985; neto $117.475. | U8: =H8-O8-P8
A9: 5 | B9: Honorarios, persona jurídica | C9: Honorarios | D9: Gran contribuyente; agente RF y RIVA | E9: Persona jurídica declarante; no gran contribuyente | F9: 3000000 | G9: 570000 | H9: 3570000 | I9: 0.11 | J9: 330000 | K9: 0.15 | L9: 85500 | M9: 0 | N9: 0 | O9: 415500 | P9: 3154500 | Q9: D 5110 / D 240805 / C 220505; pago C 236515 / C 236701 | R9: Factura, certificado RF, certificado reteIVA, comprobante, Formulario 350 | S9: Usar 4% de servicios generales; olvidar reteIVA | T9: Honorarios tienen tarifa distinta a servicios generales. | U9: =H9-O9-P9
A10: 6 | B10: Honorarios, persona natural no declarante | C10: Honorarios | D10: SAS normal; agente RF; no RIVA | E10: Persona natural no declarante; responsable de IVA | F10: 800000 | G10: 152000 | H10: 952000 | I10: 0.1 | J10: 80000 | K10: 0 | L10: 0 | M10: 0 | N10: 0 | O10: 80000 | P10: 872000 | Q10: D 5110 / D 240805 / C 220505; pago C 236515 | R10: RUT, certificación de no declarante, factura, certificado RF, Formulario 350 | S10: Aplicar 11%; practicar reteIVA sin ser agente | T10: La tarifa de no declarante es 10%. | U10: =H10-O10-P10
A11: 7 | B11: Arrendamiento de vivienda | C11: Arrendamiento inmueble | D11: SAS normal; agente RF | E11: Persona natural declarante; no gran contribuyente | F11: 1200000 | G11: 0 | H11: 1200000 | I11: 0.035 | J11: 42000 | K11: 0 | L11: 0 | M11: 0 | N11: 0 | O11: 42000 | P11: 1158000 | Q11: D 5120 / C 220505; pago C 236530 | R11: Contrato, factura o documento equivalente, certificado RF, comprobante | S11: Cobrar IVA a vivienda; aplicar reteIVA sin IVA; olvidar el mínimo de 10 UVT | T11: Arrendamiento de vivienda: IVA excluido, base supera 10 UVT. | U11: =H11-O11-P11
A12: 8 | B12: Compra de mercancía, proveedor declarante | C12: Mercancía | D12: Gran contribuyente; agente RF y RIVA | E12: Persona jurídica declarante; no gran contribuyente | F12: 4000000 | G12: 760000 | H12: 4760000 | I12: 0.025 | J12: 100000 | K12: 0.15 | L12: 114000 | M12: 0 | N12: 0 | O12: 214000 | P12: 4546000 | Q12: D 1435 / D 240805 / C 220505; pago C 236540 / C 236701 | R12: Factura, certificado RF, certificado reteIVA, comprobante, Formulario 350 | S12: Calcular RF sobre el total con IVA; olvidar el mínimo de 10 UVT | T12: Caso base de compra de mercancía. | U12: =H12-O12-P12
A13: 9 | B13: Compra de mercancía, proveedor no declarante | C13: Mercancía | D13: SAS normal; agente RF; no RIVA | E13: Persona natural no declarante; responsable de IVA | F13: 1000000 | G13: 190000 | H13: 1190000 | I13: 0.035 | J13: 35000 | K13: 0 | L13: 0 | M13: 0 | N13: 0 | O13: 35000 | P13: 1155000 | Q13: D 1435 / D 240805 / C 220505; pago C 236540 | R13: RUT, certificación de no declarante, factura, certificado RF, Formulario 350 | S13: Aplicar 2,5%; no documentar la condición de no declarante | T13: La tarifa de compras para no declarante es 3,5%. | U13: =H13-O13-P13
A14: 10 | B14: Gran contribuyente, servicio | C14: Servicio general | D14: Gran contribuyente; agente RF y RIVA | E14: Persona jurídica declarante; no gran contribuyente | F14: 5000000 | G14: 950000 | H14: 5950000 | I14: 0.04 | J14: 200000 | K14: 0.15 | L14: 142500 | M14: 0 | N14: 0 | O14: 342500 | P14: 5607500 | Q14: D 5135 / D 240805 / C 220505; pago C 236525 / C 236701 | R14: Factura, certificado RF, certificado reteIVA, comprobante, Formulario 350 | S14: Olvidar reteIVA por ser gran contribuyente; calcular sobre el total | T14: El comprador es gran contribuyente y agente de reteIVA. | U14: =H14-O14-P14
A15: 11 | B15: ReteICA en Bogotá | C15: Servicio general | D15: SAS normal; agente RF y reteICA; no RIVA | E15: Persona jurídica declarante; no gran contribuyente | F15: 2000000 | G15: 380000 | H15: 2380000 | I15: 0.04 | J15: 80000 | K15: 0 | L15: 0 | M15: 0.00966 | N15: 19320 | O15: 99320 | P15: 2280680 | Q15: D 5135 / D 240805 / C 220505; pago C 236525 / C 2368 | R15: Factura, certificado RF, certificado reteICA, comprobante, Formulario 350 | S15: Usar una tarifa de ICA de otra ciudad; no verificar la calidad de agente municipal | T15: Tarifa pedagógica 0,966% de Bogotá; verificar tarifa vigente. | U15: =H15-O15-P15
A16: 12 | B16: Proveedor SIMPLE | C16: Servicio general | D16: Gran contribuyente; agente RF y RIVA | E16: Contribuyente del SIMPLE; responsable de IVA | F16: 1000000 | G16: 190000 | H16: 1190000 | I16: 0 | J16: 0 | K16: 0.15 | L16: 28500 | M16: 0 | N16: 0 | O16: 28500 | P16: 1161500 | Q16: D 5135 / D 240805 / C 220505; pago C 236701 | R16: Factura, certificado reteIVA, comprobante; no certificado de RF | S16: Practicar retefuente a un proveedor SIMPLE; olvidar reteIVA | T16: Art. 911 ET: no hay retefuente; reteICA tampoco. | U16: =H16-O16-P16
... A20: 16 | B20: Nota crédito antes del pago | C20: Servicio general | D20: SAS normal; agente RF; no RIVA | E20: Persona jurídica declarante; no gran contribuyente | F20: 1000000 | G20: 190000 | H20: 1190000 | I20: 0.04 | J20: 40000 | K20: 0 | L20: 0 | M20: 0 | N20: 0 | O20: 40000 | P20: 1150000 | Q20: D 5135 / D 240805 / C 220505; NC 50%; pago C 236525 | R20: Factura original, nota crédito, certificado RF sobre el saldo, comprobante | S20: Retener sobre la factura original completa; no reversar la retención de la nota crédito | T20: Factura original 2.000.000 + IVA 380.000; NC 50% por 1.190.000; saldo 1.190.000; RF 40.000. | U20: =H20-O20-P20
A22: Chequeo = Total − Total retenciones − Neto. Debe ser 0 en todas las filas. Caso 4 usa valores exactos con decimales; los demás están en pesos enteros.

Sheet Resumen
A1: Resumen de cobertura
A2: Indicadores de la tabla de control. Los totales monetarios son referenciales, no una declaración.
A4: INDICADORES
B5: Casos totales | C5: =COUNTA(Casos!A5:A20) | D5: 16 casos del paquete.
B6: Casos con retefuente | C6: =COUNTIF(Casos!J5:J20,">0") | D6: Incluye servicios, honorarios, arrendamiento y compras.
B7: Casos con reteIVA | C7: =COUNTIF(Casos!L5:L20,">0") | D7: Solo cuando el comprador es agente de reteIVA.
B8: Casos con reteICA | C8: =COUNTIF(Casos!N5:N20,">0") | D8: Caso 11: tarifa pedagógica de Bogotá.
B9: Casos sin retención | C9: =COUNTIF(Casos!O5:O20,0) | D9: Caso 3: base inferior al mínimo.
B10: Suma de retenciones (referencial) | C10: =SUM(Casos!O5:O20) | D10: No sumar para una declaración; cada caso es independiente.
B11: Chequeo total (debe ser 0) | C11: =SUM(Casos!U5:U20) | D11: Si no es 0, revisar fórmulas.
A14: COBERTURA POR CONCEPTO
B15: Concepto | C15: Casos | D15: Observación
B16: Servicio general | C16: =COUNTIF(Casos!C5:C20,"Servicio general") | D16: Casos 1, 2, 3, 4, 10, 11, 12, 13, 14, 15 y 16.
B17: Honorarios | C17: =COUNTIF(Casos!C5:C20,"Honorarios") | D17: Casos 5 y 6.
B18: Arrendamiento inmueble | C18: =COUNTIF(Casos!C5:C20,"Arrendamiento inmueble") | D18: Caso 7.
B19: Mercancía | C19: =COUNTIF(Casos!C5:C20,"Mercancía") | D19: Casos 8 y 9.
A22: La tabla es un instrumento de control y aprendizaje. No reemplaza la validación del contador ni la consulta de la norma vigente.

Sheet Reglas
A1: Reglas y mínimos usados
A2: Base pedagógica del proyecto. Verifica siempre la vigencia y el RUT del proveedor.
A4: PARÁMETROS 2026
B5: Concepto | C5: Valor | D5: Observación
B6: UVT 2026 | C6: $52.374 | D6: Valor de referencia del ejercicio.
B7: 2 UVT | C7: $104.748 | D7: Mínimo de servicios.
B8: 10 UVT | C8: $523.740 | D8: Mínimo de compras y arrendamiento de inmuebles.
B9: IVA general | C9: 19% | D9: Operaciones gravadas.
B10: Retefuente servicios | C10: 4% declarante / 6% no declarante | D10: Base antes de IVA; mínimo 2 UVT.
B11: Retefuente honorarios | C11: 11% jurídica declarante / 10% no declarante | D11: Sin mínimo general; verificar excepción de 3.300 UVT.
B12: Retefuente compras | C12: 2,5% declarante / 3,5% no declarante | D12: Base antes de IVA; mínimo 10 UVT.
B13: Retefuente arrendamiento inmueble | C13: 3,5% | D13: Mínimo 10 UVT; vivienda con IVA excluido.
B14: ReteIVA | C14: 15% del IVA | D14: Solo si el comprador es agente de reteIVA.
B15: ReteICA | C15: Tarifa municipal | D15: Caso 11 usa 0,966% de Bogotá como ejemplo pedagógico.
A17: BANDERAS DEL COMPRADOR Y DEL PROVEEDOR
B18: Bandera | C18: Efecto | D18: Regla
B19: Comprador agente de retefuente | C19: Aplica RF | D19: Si no es agente, no practica retención.
B20: Comprador agente de reteIVA | C20: Aplica 15% del IVA | D20: No todos los agentes de RF son agentes de reteIVA.
B21: Comprador agente de reteICA | C21: Aplica tarifa municipal | D21: Depende del municipio y de la designación.
B22: Proveedor declarante | C22: Tarifa general | D22: Persona jurídica o natural obligada a declarar.
B23: Proveedor no declarante | C23: Tarifa incrementada | D23: Se debe documentar la condición.
B24: Proveedor SIMPLE | C24: No RF / no ICA | D24: Art. 911 ET; revisar excepciones.
B25: Proveedor autorretenedor | C25: No RF del comprador | D25: El proveedor se autorretiene; el comprador puede practicar reteIVA.
A28: Fuentes de referencia: Estatuto Tributario arts. 381, 437-1, 462-1 y 911; Decreto 572 de 2025; Auto 30229 de 2026; tabla municipal de ICA. La tabla oficial y la norma vigente prevalecen.

Sheet Checklist
A1: Checklist de revisión
A2: Marca cada caso cuando hayas validado cálculo, asiento, documentos y errores.
A4: # | B4: Caso | C4: Cálculo | D4: Asiento | E4: Documentos | F4: Errores a evitar | G4: Estado
A5: 1 | B5: Servicio general, proveedor declarante, comprador SAS normal | C5: Base 2,000,000 + IVA 380,000.00; RF 80,000.00; RIVA 0.00; RICA 0.00. | D5: D 5135 / D 240805 / C 220505; pago C 236525 | E5: Factura, certificado RF, comprobante, Formulario 350 | F5: No calcular RF sobre el total; no practicar RIVA sin ser agente | G5: Pendiente
A6: 2 | B6: Servicio general, proveedor no declarante | C6: Base 500,000 + IVA 95,000.00; RF 30,000.00; RIVA 0.00; RICA 0.00. | D6: D 5135 / D 240805 / C 220505; pago C 236525 | E6: RUT, certificación de no declarante, factura, certificado RF, Formulario 350 | F6: Aplicar 4% en lugar de 6%; no documentar la condición de no declarante | G6: Pendiente
A7: 3 | B7: Servicio por debajo del mínimo | C7: Base 90,000 + IVA 17,100.00; RF 0.00; RIVA 0.00; RICA 0.00. | D7: D 5135 / D 240805 / C 111005 (o proveedores) | E7: Factura y comprobante de pago; no hay certificado de retención | F7: Retener sobre $90.000; aplicar reteIVA sin verificar el mínimo; fragmentar la operación | G7: Pendiente
A8: 4 | B8: Base exactamente en 2 UVT | C8: Base 104,748 + IVA 19,902.12; RF 4,189.92; RIVA 2,985.32; RICA 0.00. | D8: D 5135 / D 240805 / C 220505; pago C 236525 / C 236701 | E8: Factura, certificado RF, certificado reteIVA, comprobante, Formulario 350 | F8: Redondear de forma inconsistente; no definir política de redondeo | G8: Pendiente
A9: 5 | B9: Honorarios, persona jurídica | C9: Base 3,000,000 + IVA 570,000.00; RF 330,000.00; RIVA 85,500.00; RICA 0.00. | D9: D 5110 / D 240805 / C 220505; pago C 236515 / C 236701 | E9: Factura, certificado RF, certificado reteIVA, comprobante, Formulario 350 | F9: Usar 4% de servicios generales; olvidar reteIVA | G9: Pendiente
A10: 6 | B10: Honorarios, persona natural no declarante | C10: Base 800,000 + IVA 152,000.00; RF 80,000.00; RIVA 0.00; RICA 0.00. | D10: D 5110 / D 240805 / C 220505; pago C 236515 | E10: RUT, certificación de no declarante, factura, certificado RF, Formulario 350 | F10: Aplicar 11%; practicar reteIVA sin ser agente | G10: Pendiente
A11: 7 | B11: Arrendamiento de vivienda | C11: Base 1,200,000 + IVA 0.00; RF 42,000.00; RIVA 0.00; RICA 0.00. | D11: D 5120 / C 220505; pago C 236530 | E11: Contrato, factura o documento equivalente, certificado RF, comprobante | F11: Cobrar IVA a vivienda; aplicar reteIVA sin IVA; olvidar el mínimo de 10 UVT | G11: Pendiente
A12: 8 | B12: Compra de mercancía, proveedor declarante | C12: Base 4,000,000 + IVA 760,000.00; RF 100,000.00; RIVA 114,000.00; RICA 0.00. | D12: D 1435 / D 240805 / C 220505; pago C 236540 / C 236701 | E12: Factura, certificado RF, certificado reteIVA, comprobante, Formulario 350 | F12: Calcular RF sobre el total con IVA; olvidar el mínimo de 10 UVT | G12: Pendiente
A13: 9 | B13: Compra de mercancía, proveedor no declarante | C13: Base 1,000,000 + IVA 190,000.00; RF 35,000.00; RIVA 0.00; RICA 0.00. | D13: D 1435 / D 240805 / C 220505; pago C 236540 | E13: RUT, certificación de no declarante, factura, certificado RF, Formulario 350 | F13: Aplicar 2,5%; no documentar la condición de no declarante | G13: Pendiente
A14: 10 | B14: Gran contribuyente, servicio | C14: Base 5,000,000 + IVA 950,000.00; RF 200,000.00; RIVA 142,500.00; RICA 0.00. | D14: D 5135 / D 240805 / C 220505; pago C 236525 / C 236701 | E14: Factura, certificado RF, certificado reteIVA, comprobante, Formulario 350 | F14: Olvidar reteIVA por ser gran contribuyente; calcular sobre el total | G14: Pendiente
A15: 11 | B15: ReteICA en Bogotá | C15: Base 2,000,000 + IVA 380,000.00; RF 80,000.00; RIVA 0.00; RICA 19,320.00. | D15: D 5135 / D 240805 / C 220505; pago C 236525 / C 2368 | E15: Factura, certificado RF, certificado reteICA, comprobante, Formulario 350 | F15: Usar una tarifa de ICA de otra ciudad; no verificar la calidad de agente municipal | G15: Pendiente
A16: 12 | B16: Proveedor SIMPLE | C16: Base 1,000,000 + IVA 190,000.00; RF 0.00; RIVA 28,500.00; RICA 0.00. | D16: D 5135 / D 240805 / C 220505; pago C 236701 | E16: Factura, certificado reteIVA, comprobante; no certificado de RF | F16: Practicar retefuente a un proveedor SIMPLE; olvidar reteIVA | G16: Pendiente
... A20: 16 | B20: Nota crédito antes del pago | C20: Base 1,000,000 + IVA 190,000.00; RF 40,000.00; RIVA 0.00; RICA 0.00. | D20: D 5135 / D 240805 / C 220505; NC 50%; pago C 236525 | E20: Factura original, nota crédito, certificado RF sobre el saldo, comprobante | F20: Retener sobre la factura original completa; no reversar la retención de la nota crédito | G20: Pendiente

Sheet Fuentes
A1: Fuentes y alcance
A2: Documentación de referencia del proyecto.
A4: FUENTES
B5: Estatuto Tributario | C5: Arts. 381 (certificado de retención), 437-1 (IVA), 462-1 (reteIVA), 911 (SIMPLE).
B6: Decreto 572 de 2025 | C6: Modificaciones a retenciones; base mínima de servicios de 2 UVT.
B7: Auto 30229 de 2026 | C7: Decisión del Consejo de Estado sobre la suspensión y vigencia.
B8: UVT 2026 | C8: $52.374; 2 UVT = $104.748; 10 UVT = $523.740.
B9: Tabla municipal de ICA | C9: Tarifas y mínimos por municipio; el caso 11 usa 0,966% de Bogotá como ejemplo.
A12: ALCANCE Y LÍMITES
B13: • Casos educativos con datos ficticios.
B14: • No incluye renta, nómina, pagos al exterior, AIU especial, prorrata de IVA ni moneda extranjera.
B15: • No reemplaza la revisión de un contador ni la consulta de la norma vigente.
B16: • Las tarifas y mínimos deben validarse contra el RUT, el concepto, el municipio y la fecha de la operación.
